<?xml version="1.0" encoding="UTF-8"?><record_update table="sys_rte_eb_field_mapping">
    <sys_rte_eb_field_mapping action="DELETE">
        <order>100</order>
        <referenced_sys_rte_eb_entity/>
        <source_sys_rte_eb_field display_value="serial_number_mac_cleansed_1">ba0a3acf47032110acb08f22736d4308</source_sys_rte_eb_field>
        <sys_class_name>sys_rte_eb_field_mapping</sys_class_name>
        <sys_created_by>erik.anderson</sys_created_by>
        <sys_created_on>2023-10-17 16:13:03</sys_created_on>
        <sys_id>a572efff4775b910acb08f22736d4313</sys_id>
        <sys_mod_count>0</sys_mod_count>
        <sys_name/>
        <sys_package display_value="Scheduled Job Demo" source="x_156954_sch_job_d">70e6fe8b47032110acb08f22736d4308</sys_package>
        <sys_policy/>
        <sys_rte_eb_definition display_value="Example RTE Import (Single Column)">e649f68f47032110acb08f22736d43d2</sys_rte_eb_definition>
        <sys_rte_eb_entity_mapping display_value="temp.network_interfaces[*]ToNetwork Adapter 1">6a626fff4775b910acb08f22736d4351</sys_rte_eb_entity_mapping>
        <sys_scope display_value="Scheduled Job Demo">70e6fe8b47032110acb08f22736d4308</sys_scope>
        <sys_update_name>sys_rte_eb_field_mapping_a572efff4775b910acb08f22736d4313</sys_update_name>
        <sys_updated_by>erik.anderson</sys_updated_by>
        <sys_updated_on>2023-10-17 16:13:03</sys_updated_on>
        <target_sys_rte_eb_field/>
    </sys_rte_eb_field_mapping>
    <sys_update_version action="INSERT_OR_UPDATE">
        <action>DELETE</action>
        <application display_value="Scheduled Job Demo">70e6fe8b47032110acb08f22736d4308</application>
        <file_path/>
        <instance_id>8f3db847db8a9d508aea21c4059619e6</instance_id>
        <instance_name>dev136818</instance_name>
        <name>sys_rte_eb_field_mapping_a572efff4775b910acb08f22736d4313</name>
        <payload><![CDATA[<?xml version="1.0" encoding="UTF-8"?><record_update table="sys_rte_eb_field_mapping"><sys_rte_eb_field_mapping action="INSERT_OR_UPDATE"><order>100</order><referenced_sys_rte_eb_entity/><source_sys_rte_eb_field display_value="serial_number_mac_cleansed_1">ba0a3acf47032110acb08f22736d4308</source_sys_rte_eb_field><sys_class_name>sys_rte_eb_field_mapping</sys_class_name><sys_created_by>erik.anderson</sys_created_by><sys_created_on>2023-10-17 16:13:03</sys_created_on><sys_id>a572efff4775b910acb08f22736d4313</sys_id><sys_mod_count>0</sys_mod_count><sys_name/><sys_package display_value="Scheduled Job Demo" source="x_156954_sch_job_d">70e6fe8b47032110acb08f22736d4308</sys_package><sys_policy/><sys_rte_eb_definition display_value="Example RTE Import (Single Column)">e649f68f47032110acb08f22736d43d2</sys_rte_eb_definition><sys_rte_eb_entity_mapping display_value="temp.network_interfaces[*]ToNetwork Adapter 1">6a626fff4775b910acb08f22736d4351</sys_rte_eb_entity_mapping><sys_scope display_value="Scheduled Job Demo">70e6fe8b47032110acb08f22736d4308</sys_scope><sys_update_name>sys_rte_eb_field_mapping_a572efff4775b910acb08f22736d4313</sys_update_name><sys_updated_by>erik.anderson</sys_updated_by><sys_updated_on>2023-10-17 16:13:03</sys_updated_on><target_sys_rte_eb_field/></sys_rte_eb_field_mapping></record_update>]]></payload>
        <payload_hash>343550321</payload_hash>
        <record_name/>
        <reverted_from/>
        <source>b0e6fe8b47032110acb08f22736d430a</source>
        <source_table>sys_update_set</source_table>
        <state>previous</state>
        <sys_created_by>erik.anderson</sys_created_by>
        <sys_created_on>2023-10-17 16:30:47</sys_created_on>
        <sys_id>6186a37747b5b910acb08f22736d4352</sys_id>
        <sys_mod_count>0</sys_mod_count>
        <sys_recorded_at>18b3e79bd700000001</sys_recorded_at>
        <sys_updated_by>erik.anderson</sys_updated_by>
        <sys_updated_on>2023-10-17 16:30:47</sys_updated_on>
        <type>RTE Field Mapping</type>
        <update_guid>2d72efff4675b910036115be4529a314</update_guid>
        <update_guid_history>2d72efff4675b910036115be4529a314:1012978835,2d72efff4675b910036115be4529a314:1012978835</update_guid_history>
    </sys_update_version>
    <sys_metadata_delete action="INSERT_OR_UPDATE">
        <sys_audit_delete/>
        <sys_class_name>sys_metadata_delete</sys_class_name>
        <sys_created_by>erik.anderson</sys_created_by>
        <sys_created_on>2023-10-17 16:30:48</sys_created_on>
        <sys_db_object display_value="" name="sys_rte_eb_field_mapping">sys_rte_eb_field_mapping</sys_db_object>
        <sys_id>b49b23714cab484c94f8634bd1ee6b10</sys_id>
        <sys_metadata>a572efff4775b910acb08f22736d4313</sys_metadata>
        <sys_mod_count>0</sys_mod_count>
        <sys_name/>
        <sys_package display_value="Scheduled Job Demo" source="x_156954_sch_job_d">70e6fe8b47032110acb08f22736d4308</sys_package>
        <sys_parent/>
        <sys_policy/>
        <sys_scope display_value="Scheduled Job Demo">70e6fe8b47032110acb08f22736d4308</sys_scope>
        <sys_scope_delete display_value="">1781717e76114668a6ec793f6b594110</sys_scope_delete>
        <sys_update_name>sys_rte_eb_field_mapping_a572efff4775b910acb08f22736d4313</sys_update_name>
        <sys_update_version display_value="sys_rte_eb_field_mapping_a572efff4775b910acb08f22736d4313">6186a37747b5b910acb08f22736d4352</sys_update_version>
        <sys_updated_by>erik.anderson</sys_updated_by>
        <sys_updated_on>2023-10-17 16:30:48</sys_updated_on>
    </sys_metadata_delete>
</record_update>
